tex_engine/__init__.py
tex_engine/compiler.py
tex_engine/exceptions.py
tex_engine/fragment.py
tex_engine/helper.py
tex_engine/node.py
tex_engine/template.py
tex_engine/vars.py
tex_engine-0.1.2.1.dist-info/WHEEL
tex_engine-0.1.2.1.dist-info/METADATA
tex_engine-0.1.2.1.dist-info/RECORD
